README.rst
setup.cfg
setup.py
PUBGIS.egg-info/PKG-INFO
PUBGIS.egg-info/SOURCES.txt
PUBGIS.egg-info/dependency_links.txt
PUBGIS.egg-info/requires.txt
PUBGIS.egg-info/top_level.txt
pubgis/VERSION
pubgis/__init__.py
pubgis/__main__.py
pubgis/color.py
pubgis/gui.py
pubgis/match.py
pubgis/pubgis_gui.ui
pubgis/support.py
pubgis/images/full_map.jpg
pubgis/images/land_mask.jpg
pubgis/minimap_iterators/__init__.py
pubgis/minimap_iterators/generic.py
pubgis/minimap_iterators/images.py
pubgis/minimap_iterators/live.py
pubgis/minimap_iterators/video.py