Metadata-Version: 1.2
Name: PUBGIS
Version: 0.2.4
Summary: PUBG Location Tracker
Home-page: https://github.com/andrewzwicky/PUBGIS
Author: Andrew Zwicky
Author-email: andrew.zwicky@gmail.com
License: GPLv3
Platform: UNKNOWN
Classifier: Development Status :: 3 - Alpha
Classifier: Environment :: X11 Applications :: Qt
Classifier: Intended Audience :: Developers
Classifier: License :: OSI Approved :: GNU General Public License v3 (GPLv3)
Classifier: Topic :: Games/Entertainment :: First Person Shooters
Classifier: Topic :: Multimedia :: Graphics :: Capture :: Screen Capture
Classifier: Topic :: Multimedia :: Video :: Capture
Classifier: Topic :: Utilities
Classifier: Programming Language :: Python :: 3.6
Requires-Python: >=3.6
